<BundleInfo name="ChimeraX-AtomSearchLibrary" version="1.0"
            package="chimerax.atom_search_lib" purePython="false"
            installedIncludeDir="include" installedLibraryDir="lib"
            minSessionVersion="1" maxSessionVersion="1">

  <Author>UCSF RBVI</Author>
  <Email>chimerax@cgl.ucsf.edu</Email>
  <URL>https://www.rbvi.ucsf.edu/chimerax/</URL>

  <Synopsis>3D atom search support library</Synopsis>
  <Description>C++ library for quickly search 3D space for atom within a certain distance of another atom or a xyz point.</Description>

  <Categories>
    <Category name="Structure Analysis"/>
  </Categories>

  <CLibrary name="atomsearch">
    <SourceFile>search_cpp/search.cpp</SourceFile>
    <Library>atomstruct</Library>
  </CLibrary>

  <ExtraFiles>
    <ExtraFile source="search_cpp/search.h">include/atomsearch/search.h</ExtraFile>
    <ExtraFile source="search_cpp/imex.h">include/atomsearch/imex.h</ExtraFile>
  </ExtraFiles>

  <CModule name="_load_libs">
    <SourceFile>search_cpp/load_libs.cpp</SourceFile>
	<IncludeDir>src/include</IncludeDir>
	<LibraryDir>src/lib</LibraryDir>
    <Library>atomstruct</Library>
    <Library>atomsearch</Library>
  </CModule>

  <Dependencies>
    <Dependency name="ChimeraX-Core" version="~=1.0"/>
    <Dependency name="ChimeraX-AtomicLibrary" build="true" version="~=3.0"/>
  </Dependencies>

  <Classifiers>
    <PythonClassifier>Development Status :: 2 - Pre-Alpha</PythonClassifier>
    <PythonClassifier>License :: Free for non-commercial use</PythonClassifier>
  </Classifiers>

</BundleInfo>
